commomacrossoverbacktest/__init__.py
commomacrossoverbacktest/commo_backtest.py
commomacrossoverbacktest/commo_broker.py
commomacrossoverbacktest/commo_informations.py
commomacrossoverbacktest/commomacrossoverbacktest.py
commomacrossoverbacktest/exponentialmovingaverage.py
commomacrossoverbacktest-0.2.0.dist-info/LICENSE
commomacrossoverbacktest-0.2.0.dist-info/METADATA
commomacrossoverbacktest-0.2.0.dist-info/WHEEL
commomacrossoverbacktest-0.2.0.dist-info/RECORD
