Metadata-Version: 2.3
Name: commomacrossoverbacktest
Version: 0.2.0
Summary: Python project designed to develop and implement backtesting for moving average crossover strategies applied to commodities underlyings
License: MIT
Author: Alexandre Cohen-Skalli
Requires-Python: >=3.10,<4.0
Classifier: License :: OSI Approved :: MIT License
Classifier: Programming Language :: Python :: 3
Classifier: Programming Language :: Python :: 3.10
Classifier: Programming Language :: Python :: 3.11
Classifier: Programming Language :: Python :: 3.12
Classifier: Programming Language :: Python :: 3.13
Requires-Dist: matplotlib (>=3.10.0,<4.0.0)
Requires-Dist: numba (>=0.60.0,<0.61.0)
Requires-Dist: pandas (>=2.2.3,<3.0.0)
Requires-Dist: pybacktestchain (>=0.2.1,<0.3.0)
